setup.py
mortasoft/archivos.py
mortasoft/colores.py
mortasoft.egg-info/PKG-INFO
mortasoft.egg-info/SOURCES.txt
mortasoft.egg-info/dependency_links.txt
mortasoft.egg-info/not-zip-safe
mortasoft.egg-info/requires.txt
mortasoft.egg-info/top_level.txt