Metadata-Version: 1.0
Name: mortasoft
Version: 0.12
Summary: Librerias de Mortasoft.xyz
Home-page: http://github.com/mortasoft
Author: Mortasoft
Author-email: mortasoft@gmail.com
License: MIT
Platform: UNKNOWN
